{
    "Airliner": {
        "apps": {
            "MPU9250": {
                "operations": {
                  "Noop":                 { "airliner_mid":  "0x1b53" },
                  "Reset":                { "airliner_mid":  "0x1b53" },
                  "SendDiag":             { "airliner_mid":  "0x1b53" },
                  "SetCalibration":       { "airliner_mid":  "0x1b53" },
                  "MPU9250_DiagPacket_t": { "airliner_mid":  "0x0b52" },
                  "MPU9250_HkTlm_t":      { "airliner_mid":  "0x0b51" },
                  "Measure":              { "airliner_mid":  "0x1b54" },
                  "SendHk":               { "airliner_mid":  "0x1b50" }
                },
                "config": {
                }
            }
        }
    }
}
