{
  "result": {
    "discussions": [
      {
        "anchor": {
          "fileId": "/fsw/src/mpc_app.cpp", 
          "inlineInRevision": "2da519324634de7833bb5e99811e0e114beeef46", 
          "range": {
            "endOffset": 69715, 
            "startOffset": 69615
          }, 
          "revisionId": "2da519324634de7833bb5e99811e0e114beeef46"
        }, 
        "comments": [
          {
            "authorId": "d305725e-2625-4f60-b236-48b992712339", 
            "commentId": "e3b95211-95c6-4d7e-b872-c9c74cf64e2a", 
            "date": 1524681472640, 
            "discussionId": "1524681472614#mpc#01f86a84-d146-408c-b966-afd0946f5a36", 
            "isEditable": false, 
            "isRead": false, 
            "isSynchronized": false, 
            "text": "Other magic numbers"
          }, 
          {
            "authorId": "2341ceb4-84b0-4a9c-a202-f03c1607da67", 
            "commentId": "39c9d6e7-a04b-4e25-a64b-cf44ef2ff83b", 
            "date": 1525272025518, 
            "discussionId": "1524681472614#mpc#01f86a84-d146-408c-b966-afd0946f5a36", 
            "isEditable": false, 
            "isRead": false, 
            "isSynchronized": false, 
            "parentId": "e3b95211-95c6-4d7e-b872-c9c74cf64e2a", 
            "text": "Todo: add macros."
          }
        ], 
        "discussionId": "1524681472614#mpc#01f86a84-d146-408c-b966-afd0946f5a36", 
        "isStarred": true, 
        "labels": [
          {
            "colorId": "0", 
            "id": "60aecc5f-8b7e-4672-b8bb-6c73deb05b24", 
            "name": "accept"
          }
        ], 
        "read": 2, 
        "review": {
          "reviewId": {
            "projectId": "mpc", 
            "reviewId": "MPC-CR-1"
          }, 
          "state": 1, 
          "title": "develop"
        }
      }, 
      {
        "anchor": {
          "fileId": "/fsw/src/mpc_app.cpp", 
          "inlineInRevision": "2da519324634de7833bb5e99811e0e114beeef46", 
          "range": {
            "endOffset": 69298, 
            "startOffset": 69261
          }, 
          "revisionId": "2da519324634de7833bb5e99811e0e114beeef46"
        }, 
        "comments": [
          {
            "authorId": "d305725e-2625-4f60-b236-48b992712339", 
            "commentId": "9a28ecf3-b681-4ac6-9429-2085046d4ebb", 
            "date": 1524681454840, 
            "discussionId": "1524681454813#mpc#1c346a2f-d1ab-4e3e-986b-a282ddac5663", 
            "isEditable": false, 
            "isRead": false, 
            "isSynchronized": false, 
            "text": "What are these magic numbers?"
          }, 
          {
            "authorId": "2341ceb4-84b0-4a9c-a202-f03c1607da67", 
            "commentId": "33acbfb3-6447-47a2-a3b6-7d8aab0f4e8d", 
            "date": 1525272014564, 
            "discussionId": "1524681454813#mpc#1c346a2f-d1ab-4e3e-986b-a282ddac5663", 
            "isEditable": false, 
            "isRead": false, 
            "isSynchronized": false, 
            "parentId": "9a28ecf3-b681-4ac6-9429-2085046d4ebb", 
            "text": "Todo: add macros."
          }
        ], 
        "discussionId": "1524681454813#mpc#1c346a2f-d1ab-4e3e-986b-a282ddac5663", 
        "isStarred": true, 
        "labels": [
          {
            "colorId": "0", 
            "id": "60aecc5f-8b7e-4672-b8bb-6c73deb05b24", 
            "name": "accept"
          }
        ], 
        "read": 2, 
        "review": {
          "reviewId": {
            "projectId": "mpc", 
            "reviewId": "MPC-CR-1"
          }, 
          "state": 1, 
          "title": "develop"
        }
      }, 
      {
        "anchor": {
          "fileId": "/fsw/src/mpc_app.cpp", 
          "inlineInRevision": "2da519324634de7833bb5e99811e0e114beeef46", 
          "range": {
            "endOffset": 61600, 
            "startOffset": 61536
          }, 
          "revisionId": "2da519324634de7833bb5e99811e0e114beeef46"
        }, 
        "comments": [
          {
            "authorId": "d305725e-2625-4f60-b236-48b992712339", 
            "commentId": "3988e406-e04f-4b12-ba2b-7b1d34aeafc9", 
            "date": 1524681212179, 
            "discussionId": "1524681212152#mpc#b5b95d70-7b57-495d-b71e-6eb0fb8dda0b", 
            "isEditable": false, 
            "isRead": false, 
            "isSynchronized": false, 
            "text": "Should all of this landing gear logic be here?"
          }, 
          {
            "authorId": "2341ceb4-84b0-4a9c-a202-f03c1607da67", 
            "commentId": "7c5abf51-bad8-4d66-a97b-600cb4b4d1ba", 
            "date": 1525271990755, 
            "discussionId": "1524681212152#mpc#b5b95d70-7b57-495d-b71e-6eb0fb8dda0b", 
            "isEditable": false, 
            "isRead": false, 
            "isSynchronized": false, 
            "parentId": "3988e406-e04f-4b12-ba2b-7b1d34aeafc9", 
            "text": "Todo: migrating landing gear code to lgc."
          }
        ], 
        "discussionId": "1524681212152#mpc#b5b95d70-7b57-495d-b71e-6eb0fb8dda0b", 
        "isStarred": true, 
        "labels": [
          {
            "colorId": "0", 
            "id": "60aecc5f-8b7e-4672-b8bb-6c73deb05b24", 
            "name": "accept"
          }
        ], 
        "read": 2, 
        "review": {
          "reviewId": {
            "projectId": "mpc", 
            "reviewId": "MPC-CR-1"
          }, 
          "state": 1, 
          "title": "develop"
        }
      }, 
      {
        "anchor": {
          "fileId": "/fsw/src/mpc_app.cpp", 
          "inlineInRevision": "2da519324634de7833bb5e99811e0e114beeef46", 
          "range": {
            "endOffset": 46062, 
            "startOffset": 46033
          }, 
          "revisionId": "2da519324634de7833bb5e99811e0e114beeef46"
        }, 
        "comments": [
          {
            "authorId": "3dc1e8a1-2e1f-446a-8179-97cc2b0e6423", 
            "commentId": "f509388b-fcfe-46cc-8c7b-ca4d201d3097", 
            "date": 1524677301064, 
            "discussionId": "1524677301024#mpc#5389065d-9cb4-45cc-a0a2-025c6440dd75", 
            "isEditable": false, 
            "isRead": false, 
            "isSynchronized": false, 
            "text": "Dead code"
          }, 
          {
            "authorId": "2341ceb4-84b0-4a9c-a202-f03c1607da67", 
            "commentId": "beced217-e935-4d5f-8281-9105dc1e3649", 
            "date": 1525271945976, 
            "discussionId": "1524677301024#mpc#5389065d-9cb4-45cc-a0a2-025c6440dd75", 
            "isEditable": false, 
            "isRead": false, 
            "isSynchronized": false, 
            "parentId": "f509388b-fcfe-46cc-8c7b-ca4d201d3097", 
            "text": "Todo: vtol code removal."
          }
        ], 
        "discussionId": "1524677301024#mpc#5389065d-9cb4-45cc-a0a2-025c6440dd75", 
        "isStarred": true, 
        "labels": [
          {
            "colorId": "0", 
            "id": "60aecc5f-8b7e-4672-b8bb-6c73deb05b24", 
            "name": "accept"
          }
        ], 
        "read": 2, 
        "review": {
          "reviewId": {
            "projectId": "mpc", 
            "reviewId": "MPC-CR-1"
          }, 
          "state": 1, 
          "title": "develop"
        }
      }, 
      {
        "anchor": {
          "fileId": "/fsw/src/mpc_app.cpp", 
          "inlineInRevision": "2da519324634de7833bb5e99811e0e114beeef46", 
          "range": {
            "endOffset": 39197, 
            "startOffset": 39109
          }, 
          "revisionId": "2da519324634de7833bb5e99811e0e114beeef46"
        }, 
        "comments": [
          {
            "authorId": "3dc1e8a1-2e1f-446a-8179-97cc2b0e6423", 
            "commentId": "fb3688d4-d55b-484a-809c-f57d2d3a4140", 
            "date": 1524676819782, 
            "discussionId": "1524676819753#mpc#cd6857e2-f9d9-45e3-ac48-32654f0f9652", 
            "isEditable": false, 
            "isRead": false, 
            "isSynchronized": false, 
            "text": "Isn't logic for landing gear in LGC and is this code going to be exercised."
          }, 
          {
            "authorId": "2341ceb4-84b0-4a9c-a202-f03c1607da67", 
            "commentId": "54773883-c0b8-4c86-9617-741afa7b57c3", 
            "date": 1525271924488, 
            "discussionId": "1524676819753#mpc#cd6857e2-f9d9-45e3-ac48-32654f0f9652", 
            "isEditable": false, 
            "isRead": false, 
            "isSynchronized": false, 
            "parentId": "fb3688d4-d55b-484a-809c-f57d2d3a4140", 
            "text": "Todo for landing gear code migration to lgc."
          }
        ], 
        "discussionId": "1524676819753#mpc#cd6857e2-f9d9-45e3-ac48-32654f0f9652", 
        "isStarred": true, 
        "labels": [
          {
            "colorId": "0", 
            "id": "60aecc5f-8b7e-4672-b8bb-6c73deb05b24", 
            "name": "accept"
          }
        ], 
        "read": 2, 
        "review": {
          "reviewId": {
            "projectId": "mpc", 
            "reviewId": "MPC-CR-1"
          }, 
          "state": 1, 
          "title": "develop"
        }
      }, 
      {
        "anchor": {
          "fileId": "/fsw/src/mpc_app.cpp", 
          "inlineInRevision": "2da519324634de7833bb5e99811e0e114beeef46", 
          "range": {
            "endOffset": 13244, 
            "startOffset": 13212
          }, 
          "revisionId": "2da519324634de7833bb5e99811e0e114beeef46"
        }, 
        "comments": [
          {
            "authorId": "2341ceb4-84b0-4a9c-a202-f03c1607da67", 
            "commentId": "5553c7c0-1519-418c-80a3-8043125d2761", 
            "date": 1525271798904, 
            "discussionId": "1525271798862#mpc#021540b7-03b6-4aba-9d2b-72431fcd5b2a", 
            "isEditable": false, 
            "isRead": false, 
            "isSynchronized": false, 
            "text": "Braces around case statement style."
          }
        ], 
        "discussionId": "1525271798862#mpc#021540b7-03b6-4aba-9d2b-72431fcd5b2a", 
        "isStarred": true, 
        "labels": [
          {
            "colorId": "0", 
            "id": "60aecc5f-8b7e-4672-b8bb-6c73deb05b24", 
            "name": "accept"
          }, 
          {
            "id": "style", 
            "name": "code style"
          }
        ], 
        "read": 2, 
        "review": {
          "reviewId": {
            "projectId": "mpc", 
            "reviewId": "MPC-CR-1"
          }, 
          "state": 1, 
          "title": "develop"
        }
      }, 
      {
        "anchor": {
          "fileId": "/fsw/src/mpc_config_utils.cpp", 
          "inlineInRevision": "c04e083b41d3d59042829e36c33f3269481896e4", 
          "range": {
            "endOffset": 4806, 
            "startOffset": 4720
          }, 
          "revisionId": "c04e083b41d3d59042829e36c33f3269481896e4"
        }, 
        "comments": [
          {
            "authorId": "d305725e-2625-4f60-b236-48b992712339", 
            "commentId": "25c654ff-b976-4f93-9376-483b68f82b71", 
            "date": 1524682101110, 
            "discussionId": "1524682101105#mpc#65d51903-7e95-4716-98ef-b224489e0fb5", 
            "isEditable": false, 
            "isRead": false, 
            "isSynchronized": false, 
            "text": "Address boilerplate todo"
          }
        ], 
        "discussionId": "1524682101105#mpc#65d51903-7e95-4716-98ef-b224489e0fb5", 
        "isStarred": true, 
        "labels": [
          {
            "colorId": "0", 
            "id": "60aecc5f-8b7e-4672-b8bb-6c73deb05b24", 
            "name": "accept"
          }
        ], 
        "read": 2, 
        "review": {
          "reviewId": {
            "projectId": "mpc", 
            "reviewId": "MPC-CR-1"
          }, 
          "state": 1, 
          "title": "develop"
        }
      }, 
      {
        "anchor": {
          "fileId": "/fsw/src/mpc_app.cpp", 
          "inlineInRevision": "2da519324634de7833bb5e99811e0e114beeef46", 
          "range": {
            "endOffset": 52230, 
            "startOffset": 52230
          }, 
          "revisionId": "2da519324634de7833bb5e99811e0e114beeef46"
        }, 
        "comments": [
          {
            "authorId": "d305725e-2625-4f60-b236-48b992712339", 
            "commentId": "240b1f0e-f45f-4f1d-b396-d3eee84ff64d", 
            "date": 1524681084318, 
            "discussionId": "1524681084272#mpc#7c352fb9-8166-45d9-9f5a-667a92d88441", 
            "isEditable": false, 
            "isRead": false, 
            "isSynchronized": false, 
            "text": "Remove spacing"
          }
        ], 
        "discussionId": "1524681084272#mpc#7c352fb9-8166-45d9-9f5a-667a92d88441", 
        "isStarred": true, 
        "labels": [
          {
            "colorId": "0", 
            "id": "60aecc5f-8b7e-4672-b8bb-6c73deb05b24", 
            "name": "accept"
          }
        ], 
        "read": 2, 
        "review": {
          "reviewId": {
            "projectId": "mpc", 
            "reviewId": "MPC-CR-1"
          }, 
          "state": 1, 
          "title": "develop"
        }
      }, 
      {
        "anchor": {
          "fileId": "/fsw/src/mpc_app.cpp", 
          "inlineInRevision": "2da519324634de7833bb5e99811e0e114beeef46", 
          "range": {
            "endOffset": 40069, 
            "startOffset": 40069
          }, 
          "revisionId": "2da519324634de7833bb5e99811e0e114beeef46"
        }, 
        "comments": [
          {
            "authorId": "d305725e-2625-4f60-b236-48b992712339", 
            "commentId": "7d79f9f4-8fbf-43a3-bc0c-e7fb8dcb2e3a", 
            "date": 1524680912781, 
            "discussionId": "1524680912753#mpc#b24c8417-df00-4948-ba2c-e3731e96c33a", 
            "isEditable": false, 
            "isRead": false, 
            "isSynchronized": false, 
            "text": "Remove spacing"
          }
        ], 
        "discussionId": "1524680912753#mpc#b24c8417-df00-4948-ba2c-e3731e96c33a", 
        "isStarred": true, 
        "labels": [
          {
            "colorId": "0", 
            "id": "60aecc5f-8b7e-4672-b8bb-6c73deb05b24", 
            "name": "accept"
          }
        ], 
        "read": 2, 
        "review": {
          "reviewId": {
            "projectId": "mpc", 
            "reviewId": "MPC-CR-1"
          }, 
          "state": 1, 
          "title": "develop"
        }
      }, 
      {
        "anchor": {
          "fileId": "/fsw/src/mpc_app.cpp", 
          "inlineInRevision": "2da519324634de7833bb5e99811e0e114beeef46", 
          "range": {
            "endOffset": 37529, 
            "startOffset": 37452
          }, 
          "revisionId": "2da519324634de7833bb5e99811e0e114beeef46"
        }, 
        "comments": [
          {
            "authorId": "d305725e-2625-4f60-b236-48b992712339", 
            "commentId": "7163190e-ee16-491a-a2ff-5c21dd11a0fb", 
            "date": 1524680829726, 
            "discussionId": "1524680829698#mpc#51bb98bb-9778-4c9f-8f2a-41da4b3b1f49", 
            "isEditable": false, 
            "isRead": false, 
            "isSynchronized": false, 
            "text": "Mixing comment styles"
          }
        ], 
        "discussionId": "1524680829698#mpc#51bb98bb-9778-4c9f-8f2a-41da4b3b1f49", 
        "isStarred": true, 
        "labels": [
          {
            "colorId": "0", 
            "id": "60aecc5f-8b7e-4672-b8bb-6c73deb05b24", 
            "name": "accept"
          }, 
          {
            "id": "style", 
            "name": "code style"
          }
        ], 
        "read": 2, 
        "review": {
          "reviewId": {
            "projectId": "mpc", 
            "reviewId": "MPC-CR-1"
          }, 
          "state": 1, 
          "title": "develop"
        }
      }, 
      {
        "anchor": {
          "fileId": "/fsw/src/mpc_app.cpp", 
          "inlineInRevision": "2da519324634de7833bb5e99811e0e114beeef46", 
          "range": {
            "endOffset": 30911, 
            "startOffset": 30881
          }, 
          "revisionId": "2da519324634de7833bb5e99811e0e114beeef46"
        }, 
        "comments": [
          {
            "authorId": "d305725e-2625-4f60-b236-48b992712339", 
            "commentId": "14fec2ea-9061-48fc-9ab6-e263352f06bd", 
            "date": 1524680406683, 
            "discussionId": "1524680406657#mpc#c853c2f8-d7e2-4be0-a827-f570e42b7ff1", 
            "isEditable": false, 
            "isRead": false, 
            "isSynchronized": false, 
            "text": "Initialize with values"
          }
        ], 
        "discussionId": "1524680406657#mpc#c853c2f8-d7e2-4be0-a827-f570e42b7ff1", 
        "isStarred": true, 
        "labels": [
          {
            "colorId": "0", 
            "id": "60aecc5f-8b7e-4672-b8bb-6c73deb05b24", 
            "name": "accept"
          }
        ], 
        "read": 2, 
        "review": {
          "reviewId": {
            "projectId": "mpc", 
            "reviewId": "MPC-CR-1"
          }, 
          "state": 1, 
          "title": "develop"
        }
      }, 
      {
        "anchor": {
          "fileId": "/fsw/src/mpc_app.cpp", 
          "inlineInRevision": "2da519324634de7833bb5e99811e0e114beeef46", 
          "range": {
            "endOffset": 30393, 
            "startOffset": 30393
          }, 
          "revisionId": "2da519324634de7833bb5e99811e0e114beeef46"
        }, 
        "comments": [
          {
            "authorId": "d305725e-2625-4f60-b236-48b992712339", 
            "commentId": "8c10bbe8-f96a-4363-9af4-d757243df2f3", 
            "date": 1524680373260, 
            "discussionId": "1524680373233#mpc#37aba51b-dfcf-4af9-ab81-6b16ea8013f9", 
            "isEditable": false, 
            "isRead": false, 
            "isSynchronized": false, 
            "text": "Remove excess spaces"
          }
        ], 
        "discussionId": "1524680373233#mpc#37aba51b-dfcf-4af9-ab81-6b16ea8013f9", 
        "isStarred": true, 
        "labels": [
          {
            "colorId": "0", 
            "id": "60aecc5f-8b7e-4672-b8bb-6c73deb05b24", 
            "name": "accept"
          }, 
          {
            "id": "style", 
            "name": "code style"
          }
        ], 
        "read": 2, 
        "review": {
          "reviewId": {
            "projectId": "mpc", 
            "reviewId": "MPC-CR-1"
          }, 
          "state": 1, 
          "title": "develop"
        }
      }, 
      {
        "anchor": {
          "fileId": "/fsw/src/mpc_app.cpp", 
          "inlineInRevision": "2da519324634de7833bb5e99811e0e114beeef46", 
          "range": {
            "endOffset": 26852, 
            "startOffset": 26797
          }, 
          "revisionId": "2da519324634de7833bb5e99811e0e114beeef46"
        }, 
        "comments": [
          {
            "authorId": "d305725e-2625-4f60-b236-48b992712339", 
            "commentId": "342dd1f5-beb2-44b5-b6f7-1825f8fba102", 
            "date": 1524680290634, 
            "discussionId": "1524680290605#mpc#3a4b44f1-8373-4bc8-a4a8-7ecfa9d60854", 
            "isEditable": false, 
            "isRead": false, 
            "isSynchronized": false, 
            "text": "Make macros for these magic numbers."
          }
        ], 
        "discussionId": "1524680290605#mpc#3a4b44f1-8373-4bc8-a4a8-7ecfa9d60854", 
        "isStarred": true, 
        "labels": [
          {
            "colorId": "0", 
            "id": "60aecc5f-8b7e-4672-b8bb-6c73deb05b24", 
            "name": "accept"
          }
        ], 
        "read": 2, 
        "review": {
          "reviewId": {
            "projectId": "mpc", 
            "reviewId": "MPC-CR-1"
          }, 
          "state": 1, 
          "title": "develop"
        }
      }, 
      {
        "anchor": {
          "fileId": "/fsw/src/mpc_app.cpp", 
          "inlineInRevision": "2da519324634de7833bb5e99811e0e114beeef46", 
          "range": {
            "endOffset": 77627, 
            "startOffset": 77548
          }, 
          "revisionId": "2da519324634de7833bb5e99811e0e114beeef46"
        }, 
        "comments": [
          {
            "authorId": "3dc1e8a1-2e1f-446a-8179-97cc2b0e6423", 
            "commentId": "84221d1c-8df2-4bbe-8c7d-3b7840bfcaa5", 
            "date": 1524678278237, 
            "discussionId": "1524678278210#mpc#e2425236-a76f-41cf-8b43-02eeee856156", 
            "isEditable": false, 
            "isRead": false, 
            "isSynchronized": false, 
            "text": "Global: Change all bool to boolean"
          }
        ], 
        "discussionId": "1524678278210#mpc#e2425236-a76f-41cf-8b43-02eeee856156", 
        "isStarred": true, 
        "labels": [
          {
            "colorId": "0", 
            "id": "60aecc5f-8b7e-4672-b8bb-6c73deb05b24", 
            "name": "accept"
          }
        ], 
        "read": 2, 
        "review": {
          "reviewId": {
            "projectId": "mpc", 
            "reviewId": "MPC-CR-1"
          }, 
          "state": 1, 
          "title": "develop"
        }
      }, 
      {
        "anchor": {
          "fileId": "/fsw/src/mpc_app.cpp", 
          "inlineInRevision": "2da519324634de7833bb5e99811e0e114beeef46", 
          "range": {
            "endOffset": 80824, 
            "startOffset": 80822
          }, 
          "revisionId": "2da519324634de7833bb5e99811e0e114beeef46"
        }, 
        "comments": [
          {
            "authorId": "3dc1e8a1-2e1f-446a-8179-97cc2b0e6423", 
            "commentId": "4add82ca-8b66-462b-965b-c69d6d7e5a34", 
            "date": 1524678333410, 
            "discussionId": "1524678333381#mpc#9379859c-ab45-4349-a313-b2d5463e7a72", 
            "isEditable": false, 
            "isRead": false, 
            "isSynchronized": false, 
            "text": "Else if shall be followed by else construct"
          }
        ], 
        "discussionId": "1524678333381#mpc#9379859c-ab45-4349-a313-b2d5463e7a72", 
        "isStarred": true, 
        "labels": [
          {
            "colorId": "0", 
            "id": "60aecc5f-8b7e-4672-b8bb-6c73deb05b24", 
            "name": "accept"
          }
        ], 
        "read": 2, 
        "review": {
          "reviewId": {
            "projectId": "mpc", 
            "reviewId": "MPC-CR-1"
          }, 
          "state": 1, 
          "title": "develop"
        }
      }, 
      {
        "anchor": {
          "fileId": "/fsw/src/mpc_app.cpp", 
          "inlineInRevision": "2da519324634de7833bb5e99811e0e114beeef46", 
          "range": {
            "endOffset": 77227, 
            "startOffset": 77216
          }, 
          "revisionId": "2da519324634de7833bb5e99811e0e114beeef46"
        }, 
        "comments": [
          {
            "authorId": "3dc1e8a1-2e1f-446a-8179-97cc2b0e6423", 
            "commentId": "e22a6659-960f-4fc2-acb9-c388405cae5f", 
            "date": 1524678255363, 
            "discussionId": "1524678255330#mpc#cbeb22ba-285c-4b90-9eaf-72731010a938", 
            "isEditable": false, 
            "isRead": false, 
            "isSynchronized": false, 
            "text": "Global: Initialize all such variables"
          }
        ], 
        "discussionId": "1524678255330#mpc#cbeb22ba-285c-4b90-9eaf-72731010a938", 
        "isStarred": true, 
        "labels": [
          {
            "colorId": "0", 
            "id": "60aecc5f-8b7e-4672-b8bb-6c73deb05b24", 
            "name": "accept"
          }
        ], 
        "read": 2, 
        "review": {
          "reviewId": {
            "projectId": "mpc", 
            "reviewId": "MPC-CR-1"
          }, 
          "state": 1, 
          "title": "develop"
        }
      }, 
      {
        "anchor": {
          "fileId": "/fsw/src/mpc_app.cpp", 
          "inlineInRevision": "2da519324634de7833bb5e99811e0e114beeef46", 
          "range": {
            "endOffset": 75618, 
            "startOffset": 75586
          }, 
          "revisionId": "2da519324634de7833bb5e99811e0e114beeef46"
        }, 
        "comments": [
          {
            "authorId": "3dc1e8a1-2e1f-446a-8179-97cc2b0e6423", 
            "commentId": "401f96b8-1440-4d48-9be7-ee55fd031bb4", 
            "date": 1524678199762, 
            "discussionId": "1524678199719#mpc#c8464edd-e557-4e3d-89a8-52f09287b665", 
            "isEditable": false, 
            "isRead": false, 
            "isSynchronized": false, 
            "text": "Consider declaring the variable i at the beginning of the function"
          }
        ], 
        "discussionId": "1524678199719#mpc#c8464edd-e557-4e3d-89a8-52f09287b665", 
        "isStarred": true, 
        "labels": [
          {
            "colorId": "0", 
            "id": "60aecc5f-8b7e-4672-b8bb-6c73deb05b24", 
            "name": "accept"
          }
        ], 
        "read": 2, 
        "review": {
          "reviewId": {
            "projectId": "mpc", 
            "reviewId": "MPC-CR-1"
          }, 
          "state": 1, 
          "title": "develop"
        }
      }, 
      {
        "anchor": {
          "fileId": "/fsw/src/mpc_app.cpp", 
          "inlineInRevision": "2da519324634de7833bb5e99811e0e114beeef46", 
          "range": {
            "endOffset": 71876, 
            "startOffset": 71859
          }, 
          "revisionId": "2da519324634de7833bb5e99811e0e114beeef46"
        }, 
        "comments": [
          {
            "authorId": "3dc1e8a1-2e1f-446a-8179-97cc2b0e6423", 
            "commentId": "6906841d-c36b-493b-9903-fcf0eacc6aba", 
            "date": 1524678085924, 
            "discussionId": "1524678085886#mpc#b2f65bb6-308d-40c4-9f0d-d641a20d3c9f", 
            "isEditable": false, 
            "isRead": false, 
            "isSynchronized": false, 
            "text": "Initialize the variable"
          }
        ], 
        "discussionId": "1524678085886#mpc#b2f65bb6-308d-40c4-9f0d-d641a20d3c9f", 
        "isStarred": true, 
        "labels": [
          {
            "colorId": "0", 
            "id": "60aecc5f-8b7e-4672-b8bb-6c73deb05b24", 
            "name": "accept"
          }
        ], 
        "read": 2, 
        "review": {
          "reviewId": {
            "projectId": "mpc", 
            "reviewId": "MPC-CR-1"
          }, 
          "state": 1, 
          "title": "develop"
        }
      }, 
      {
        "anchor": {
          "fileId": "/fsw/src/mpc_app.cpp", 
          "inlineInRevision": "2da519324634de7833bb5e99811e0e114beeef46", 
          "range": {
            "endOffset": 67937, 
            "startOffset": 67909
          }, 
          "revisionId": "2da519324634de7833bb5e99811e0e114beeef46"
        }, 
        "comments": [
          {
            "authorId": "3dc1e8a1-2e1f-446a-8179-97cc2b0e6423", 
            "commentId": "e84b328f-3880-4e96-853b-430a725713fe", 
            "date": 1524677839756, 
            "discussionId": "1524677839725#mpc#6d27d246-523b-497c-a948-03d79e5c3710", 
            "isEditable": false, 
            "isRead": false, 
            "isSynchronized": false, 
            "text": "Change bool to boolean"
          }
        ], 
        "discussionId": "1524677839725#mpc#6d27d246-523b-497c-a948-03d79e5c3710", 
        "isStarred": true, 
        "labels": [
          {
            "colorId": "0", 
            "id": "60aecc5f-8b7e-4672-b8bb-6c73deb05b24", 
            "name": "accept"
          }
        ], 
        "read": 2, 
        "review": {
          "reviewId": {
            "projectId": "mpc", 
            "reviewId": "MPC-CR-1"
          }, 
          "state": 1, 
          "title": "develop"
        }
      }, 
      {
        "anchor": {
          "fileId": "/fsw/src/mpc_app.cpp", 
          "inlineInRevision": "2da519324634de7833bb5e99811e0e114beeef46", 
          "range": {
            "endOffset": 60760, 
            "startOffset": 60757
          }, 
          "revisionId": "2da519324634de7833bb5e99811e0e114beeef46"
        }, 
        "comments": [
          {
            "authorId": "3dc1e8a1-2e1f-446a-8179-97cc2b0e6423", 
            "commentId": "e100ed74-efef-4ec8-af91-106b5e6e1055", 
            "date": 1524677640285, 
            "discussionId": "1524677640245#mpc#3f98979d-4ddf-4dcb-9511-11b77d09fd1b", 
            "isEditable": false, 
            "isRead": false, 
            "isSynchronized": false, 
            "text": "Required a else statement"
          }
        ], 
        "discussionId": "1524677640245#mpc#3f98979d-4ddf-4dcb-9511-11b77d09fd1b", 
        "isStarred": true, 
        "labels": [
          {
            "colorId": "0", 
            "id": "60aecc5f-8b7e-4672-b8bb-6c73deb05b24", 
            "name": "accept"
          }
        ], 
        "read": 2, 
        "review": {
          "reviewId": {
            "projectId": "mpc", 
            "reviewId": "MPC-CR-1"
          }, 
          "state": 1, 
          "title": "develop"
        }
      }, 
      {
        "anchor": {
          "fileId": "/fsw/src/mpc_app.cpp", 
          "inlineInRevision": "2da519324634de7833bb5e99811e0e114beeef46", 
          "range": {
            "endOffset": 54066, 
            "startOffset": 54029
          }, 
          "revisionId": "2da519324634de7833bb5e99811e0e114beeef46"
        }, 
        "comments": [
          {
            "authorId": "3dc1e8a1-2e1f-446a-8179-97cc2b0e6423", 
            "commentId": "eb6e6971-2941-4ee1-a083-a32def52ab9c", 
            "date": 1524677540793, 
            "discussionId": "1524677540765#mpc#8dff1c3c-9d96-410e-9f2e-63b9db33ae05", 
            "isEditable": false, 
            "isRead": false, 
            "isSynchronized": false, 
            "text": "Change type to CFE boolean"
          }
        ], 
        "discussionId": "1524677540765#mpc#8dff1c3c-9d96-410e-9f2e-63b9db33ae05", 
        "isStarred": true, 
        "labels": [
          {
            "colorId": "0", 
            "id": "60aecc5f-8b7e-4672-b8bb-6c73deb05b24", 
            "name": "accept"
          }
        ], 
        "read": 2, 
        "review": {
          "reviewId": {
            "projectId": "mpc", 
            "reviewId": "MPC-CR-1"
          }, 
          "state": 1, 
          "title": "develop"
        }
      }, 
      {
        "anchor": {
          "fileId": "/fsw/src/mpc_app.cpp", 
          "inlineInRevision": "2da519324634de7833bb5e99811e0e114beeef46", 
          "range": {
            "endOffset": 53502, 
            "startOffset": 53499
          }, 
          "revisionId": "2da519324634de7833bb5e99811e0e114beeef46"
        }, 
        "comments": [
          {
            "authorId": "3dc1e8a1-2e1f-446a-8179-97cc2b0e6423", 
            "commentId": "c263b3b0-1d5f-4466-82b4-e6f545414b69", 
            "date": 1524677510282, 
            "discussionId": "1524677510245#mpc#6504908b-f76e-4ff9-93a9-e425a417d6df", 
            "isEditable": false, 
            "isRead": false, 
            "isSynchronized": false, 
            "text": "Every else if shall be followed by an else construct"
          }
        ], 
        "discussionId": "1524677510245#mpc#6504908b-f76e-4ff9-93a9-e425a417d6df", 
        "isStarred": true, 
        "labels": [
          {
            "colorId": "0", 
            "id": "60aecc5f-8b7e-4672-b8bb-6c73deb05b24", 
            "name": "accept"
          }, 
          {
            "id": "style", 
            "name": "code style"
          }
        ], 
        "read": 2, 
        "review": {
          "reviewId": {
            "projectId": "mpc", 
            "reviewId": "MPC-CR-1"
          }, 
          "state": 1, 
          "title": "develop"
        }
      }, 
      {
        "anchor": {
          "fileId": "/fsw/src/mpc_app.cpp", 
          "inlineInRevision": "2da519324634de7833bb5e99811e0e114beeef46", 
          "range": {
            "endOffset": 48804, 
            "startOffset": 48790
          }, 
          "revisionId": "2da519324634de7833bb5e99811e0e114beeef46"
        }, 
        "comments": [
          {
            "authorId": "3dc1e8a1-2e1f-446a-8179-97cc2b0e6423", 
            "commentId": "b860d2ec-6baf-44be-b502-c19f74a3b60b", 
            "date": 1524677431907, 
            "discussionId": "1524677431867#mpc#0c59f2c3-a316-459f-9126-23ba5f68d075", 
            "isEditable": false, 
            "isRead": false, 
            "isSynchronized": false, 
            "text": "Initialize this value"
          }
        ], 
        "discussionId": "1524677431867#mpc#0c59f2c3-a316-459f-9126-23ba5f68d075", 
        "isStarred": true, 
        "labels": [
          {
            "colorId": "0", 
            "id": "60aecc5f-8b7e-4672-b8bb-6c73deb05b24", 
            "name": "accept"
          }
        ], 
        "read": 2, 
        "review": {
          "reviewId": {
            "projectId": "mpc", 
            "reviewId": "MPC-CR-1"
          }, 
          "state": 1, 
          "title": "develop"
        }
      }, 
      {
        "anchor": {
          "fileId": "/fsw/src/mpc_app.cpp", 
          "inlineInRevision": "2da519324634de7833bb5e99811e0e114beeef46", 
          "range": {
            "endOffset": 23816, 
            "startOffset": 23792
          }, 
          "revisionId": "2da519324634de7833bb5e99811e0e114beeef46"
        }, 
        "comments": [
          {
            "authorId": "d305725e-2625-4f60-b236-48b992712339", 
            "commentId": "d72cfe76-09da-4d63-b640-f41aa9d31f54", 
            "date": 1524676458988, 
            "discussionId": "1524676458956#mpc#6ab019f4-f456-48b3-8684-8ab87e098f47", 
            "isEditable": false, 
            "isRead": false, 
            "isSynchronized": false, 
            "text": "Global comment. We're mixing variable naming conventions throughout this file. Change to one"
          }
        ], 
        "discussionId": "1524676458956#mpc#6ab019f4-f456-48b3-8684-8ab87e098f47", 
        "isStarred": true, 
        "labels": [
          {
            "colorId": "0", 
            "id": "60aecc5f-8b7e-4672-b8bb-6c73deb05b24", 
            "name": "accept"
          }, 
          {
            "id": "style", 
            "name": "code style"
          }
        ], 
        "read": 2, 
        "review": {
          "reviewId": {
            "projectId": "mpc", 
            "reviewId": "MPC-CR-1"
          }, 
          "state": 1, 
          "title": "develop"
        }
      }, 
      {
        "anchor": {
          "fileId": "/fsw/src/mpc_app.cpp", 
          "inlineInRevision": "2da519324634de7833bb5e99811e0e114beeef46", 
          "range": {
            "endOffset": 32520, 
            "startOffset": 32449
          }, 
          "revisionId": "2da519324634de7833bb5e99811e0e114beeef46"
        }, 
        "comments": [
          {
            "authorId": "3dc1e8a1-2e1f-446a-8179-97cc2b0e6423", 
            "commentId": "e94d7fcf-aed7-48af-9606-1036df10d8d2", 
            "date": 1524676445038, 
            "discussionId": "1524676444999#mpc#fb24c392-4f2e-4bfe-bc3f-15d8e6a16ab8", 
            "isEditable": false, 
            "isRead": false, 
            "isSynchronized": false, 
            "text": "You may want to get rid of todo"
          }
        ], 
        "discussionId": "1524676444999#mpc#fb24c392-4f2e-4bfe-bc3f-15d8e6a16ab8", 
        "isStarred": true, 
        "labels": [
          {
            "colorId": "0", 
            "id": "60aecc5f-8b7e-4672-b8bb-6c73deb05b24", 
            "name": "accept"
          }
        ], 
        "read": 2, 
        "review": {
          "reviewId": {
            "projectId": "mpc", 
            "reviewId": "MPC-CR-1"
          }, 
          "state": 1, 
          "title": "develop"
        }
      }, 
      {
        "anchor": {
          "fileId": "/fsw/src/mpc_app.cpp", 
          "inlineInRevision": "2da519324634de7833bb5e99811e0e114beeef46", 
          "range": {
            "endOffset": 19917, 
            "startOffset": 19868
          }, 
          "revisionId": "2da519324634de7833bb5e99811e0e114beeef46"
        }, 
        "comments": [
          {
            "authorId": "d305725e-2625-4f60-b236-48b992712339", 
            "commentId": "50f8390c-6f3e-454e-b994-763ce11d9e7f", 
            "date": 1524676180604, 
            "discussionId": "1524676180573#mpc#12da9a94-6a58-4d13-8572-efea21a1a279", 
            "isEditable": false, 
            "isRead": false, 
            "isSynchronized": false, 
            "text": "Remove commented out code"
          }
        ], 
        "discussionId": "1524676180573#mpc#12da9a94-6a58-4d13-8572-efea21a1a279", 
        "isStarred": true, 
        "labels": [
          {
            "colorId": "0", 
            "id": "60aecc5f-8b7e-4672-b8bb-6c73deb05b24", 
            "name": "accept"
          }
        ], 
        "read": 2, 
        "review": {
          "reviewId": {
            "projectId": "mpc", 
            "reviewId": "MPC-CR-1"
          }, 
          "state": 1, 
          "title": "develop"
        }
      }, 
      {
        "anchor": {
          "fileId": "/fsw/src/mpc_app.cpp", 
          "inlineInRevision": "2da519324634de7833bb5e99811e0e114beeef46", 
          "range": {
            "endOffset": 15563, 
            "startOffset": 15483
          }, 
          "revisionId": "2da519324634de7833bb5e99811e0e114beeef46"
        }, 
        "comments": [
          {
            "authorId": "d305725e-2625-4f60-b236-48b992712339", 
            "commentId": "36a34498-a17c-405f-9931-95bbead914c2", 
            "date": 1524676118430, 
            "discussionId": "1524676118392#mpc#9e110ee7-6f92-4855-82f5-38d12c00b313", 
            "isEditable": false, 
            "isRead": false, 
            "isSynchronized": false, 
            "text": "Address boilerplate todo"
          }
        ], 
        "discussionId": "1524676118392#mpc#9e110ee7-6f92-4855-82f5-38d12c00b313", 
        "isStarred": true, 
        "labels": [
          {
            "colorId": "0", 
            "id": "60aecc5f-8b7e-4672-b8bb-6c73deb05b24", 
            "name": "accept"
          }
        ], 
        "read": 2, 
        "review": {
          "reviewId": {
            "projectId": "mpc", 
            "reviewId": "MPC-CR-1"
          }, 
          "state": 1, 
          "title": "develop"
        }
      }, 
      {
        "anchor": {
          "fileId": "/fsw/src/mpc_app.cpp", 
          "inlineInRevision": "2da519324634de7833bb5e99811e0e114beeef46", 
          "range": {
            "endOffset": 15281, 
            "startOffset": 15202
          }, 
          "revisionId": "2da519324634de7833bb5e99811e0e114beeef46"
        }, 
        "comments": [
          {
            "authorId": "d305725e-2625-4f60-b236-48b992712339", 
            "commentId": "af483816-0868-42c8-ad54-87b7186d78b4", 
            "date": 1524676105795, 
            "discussionId": "1524676105757#mpc#fbdc4826-8954-47f4-945c-05144c34006f", 
            "isEditable": false, 
            "isRead": false, 
            "isSynchronized": false, 
            "text": "Address boilerplate todo"
          }
        ], 
        "discussionId": "1524676105757#mpc#fbdc4826-8954-47f4-945c-05144c34006f", 
        "isStarred": true, 
        "labels": [
          {
            "colorId": "0", 
            "id": "60aecc5f-8b7e-4672-b8bb-6c73deb05b24", 
            "name": "accept"
          }
        ], 
        "read": 2, 
        "review": {
          "reviewId": {
            "projectId": "mpc", 
            "reviewId": "MPC-CR-1"
          }, 
          "state": 1, 
          "title": "develop"
        }
      }, 
      {
        "anchor": {
          "fileId": "/fsw/src/mpc_app.cpp", 
          "inlineInRevision": "2da519324634de7833bb5e99811e0e114beeef46", 
          "range": {
            "endOffset": 914, 
            "startOffset": 914
          }, 
          "revisionId": "2da519324634de7833bb5e99811e0e114beeef46"
        }, 
        "comments": [
          {
            "authorId": "d305725e-2625-4f60-b236-48b992712339", 
            "commentId": "758c60ef-1227-44b2-9030-26e448fb043c", 
            "date": 1524675982473, 
            "discussionId": "1524675982432#mpc#c5cdd54c-e77d-4056-9fd5-946a3a2818e7", 
            "isEditable": false, 
            "isRead": false, 
            "isSynchronized": false, 
            "text": "Global comment. Remove excess whitespace between functions"
          }
        ], 
        "discussionId": "1524675982432#mpc#c5cdd54c-e77d-4056-9fd5-946a3a2818e7", 
        "isStarred": true, 
        "labels": [
          {
            "colorId": "0", 
            "id": "60aecc5f-8b7e-4672-b8bb-6c73deb05b24", 
            "name": "accept"
          }
        ], 
        "read": 2, 
        "review": {
          "reviewId": {
            "projectId": "mpc", 
            "reviewId": "MPC-CR-1"
          }, 
          "state": 1, 
          "title": "develop"
        }
      }, 
      {
        "anchor": {
          "fileId": "/fsw/for_build/CMakeLists.txt", 
          "inlineInRevision": "76ba3e459e78146462424682ae643a42dafc7dc7", 
          "range": {
            "endOffset": 0, 
            "startOffset": 0
          }, 
          "revisionId": "76ba3e459e78146462424682ae643a42dafc7dc7"
        }, 
        "comments": [
          {
            "authorId": "d305725e-2625-4f60-b236-48b992712339", 
            "commentId": "bebb81a9-f79b-40db-814b-fd3c44e49418", 
            "date": 1524675837359, 
            "discussionId": "1524675837351#mpc#ffc1ea72-d388-497c-8e19-1d3c03a810f6", 
            "isEditable": false, 
            "isRead": false, 
            "isSynchronized": false, 
            "text": "License text"
          }
        ], 
        "discussionId": "1524675837351#mpc#ffc1ea72-d388-497c-8e19-1d3c03a810f6", 
        "isStarred": true, 
        "read": 2, 
        "review": {
          "reviewId": {
            "projectId": "mpc", 
            "reviewId": "MPC-CR-1"
          }, 
          "state": 1, 
          "title": "develop"
        }
      }, 
      {
        "anchor": {
          "fileId": "/fsw/src/mpc_app.cpp", 
          "inlineInRevision": "2da519324634de7833bb5e99811e0e114beeef46", 
          "range": {
            "endOffset": 16490, 
            "startOffset": 16477
          }, 
          "revisionId": "2da519324634de7833bb5e99811e0e114beeef46"
        }, 
        "comments": [
          {
            "authorId": "3dc1e8a1-2e1f-446a-8179-97cc2b0e6423", 
            "commentId": "ff749a48-0f9b-4ae2-a11d-cea8202c4b2b", 
            "date": 1524675378366, 
            "discussionId": "1524675378340#mpc#a44f5b28-ecb3-433d-8576-8d7c9ccd9c7c", 
            "isEditable": false, 
            "isRead": false, 
            "isSynchronized": false, 
            "text": "May want to change the 1 to true, Rule 5\u20130\u201313 states \"The condition of an if-statement and the condition of an iteration-statement shall have type boolean.\""
          }
        ], 
        "discussionId": "1524675378340#mpc#a44f5b28-ecb3-433d-8576-8d7c9ccd9c7c", 
        "isStarred": true, 
        "labels": [
          {
            "colorId": "0", 
            "id": "60aecc5f-8b7e-4672-b8bb-6c73deb05b24", 
            "name": "accept"
          }
        ], 
        "read": 2, 
        "review": {
          "reviewId": {
            "projectId": "mpc", 
            "reviewId": "MPC-CR-1"
          }, 
          "state": 1, 
          "title": "develop"
        }
      }, 
      {
        "anchor": {
          "fileId": "/fsw/src/mpc_app.cpp", 
          "inlineInRevision": "2da519324634de7833bb5e99811e0e114beeef46", 
          "range": {
            "endOffset": 17317, 
            "startOffset": 17291
          }, 
          "revisionId": "2da519324634de7833bb5e99811e0e114beeef46"
        }, 
        "comments": [
          {
            "authorId": "3dc1e8a1-2e1f-446a-8179-97cc2b0e6423", 
            "commentId": "5762980f-3c84-4277-946a-c040dd7bd50f", 
            "date": 1524675373718, 
            "discussionId": "1524675373679#mpc#7d22ddfe-6df1-47f8-a3d1-791bdd4aa72a", 
            "isEditable": false, 
            "isRead": false, 
            "isSynchronized": false, 
            "text": "Rule 6-6-4 states for any iteration statement, which in this case is the while loop, there shall be no more than one break or goto statement used for loop termination. See if it is possible to restructure the code"
          }
        ], 
        "discussionId": "1524675373679#mpc#7d22ddfe-6df1-47f8-a3d1-791bdd4aa72a", 
        "isStarred": true, 
        "labels": [
          {
            "colorId": "0", 
            "id": "60aecc5f-8b7e-4672-b8bb-6c73deb05b24", 
            "name": "accept"
          }
        ], 
        "read": 2, 
        "review": {
          "reviewId": {
            "projectId": "mpc", 
            "reviewId": "MPC-CR-1"
          }, 
          "state": 1, 
          "title": "develop"
        }
      }, 
      {
        "anchor": {
          "fileId": "/fsw/src/mpc_app.cpp", 
          "inlineInRevision": "2da519324634de7833bb5e99811e0e114beeef46", 
          "range": {
            "endOffset": 18192, 
            "startOffset": 18163
          }, 
          "revisionId": "2da519324634de7833bb5e99811e0e114beeef46"
        }, 
        "comments": [
          {
            "authorId": "3dc1e8a1-2e1f-446a-8179-97cc2b0e6423", 
            "commentId": "76b5dba8-d9b4-4273-b1fd-aaf5a79c83bd", 
            "date": 1524675348625, 
            "discussionId": "1524675348597#mpc#373daaee-4d21-42b2-92cf-04333c4164c9", 
            "isEditable": false, 
            "isRead": false, 
            "isSynchronized": false, 
            "text": "case and default constructs shall be enclosed in curly braces"
          }
        ], 
        "discussionId": "1524675348597#mpc#373daaee-4d21-42b2-92cf-04333c4164c9", 
        "isStarred": true, 
        "labels": [
          {
            "colorId": "0", 
            "id": "60aecc5f-8b7e-4672-b8bb-6c73deb05b24", 
            "name": "accept"
          }
        ], 
        "read": 2, 
        "review": {
          "reviewId": {
            "projectId": "mpc", 
            "reviewId": "MPC-CR-1"
          }, 
          "state": 1, 
          "title": "develop"
        }
      }, 
      {
        "anchor": {
          "fileId": "/fsw/src/mpc_app.cpp", 
          "inlineInRevision": "2da519324634de7833bb5e99811e0e114beeef46", 
          "range": {
            "endOffset": 15136, 
            "startOffset": 15072
          }, 
          "revisionId": "2da519324634de7833bb5e99811e0e114beeef46"
        }, 
        "comments": [
          {
            "authorId": "3dc1e8a1-2e1f-446a-8179-97cc2b0e6423", 
            "commentId": "4e2b4a5e-657e-4c87-b88d-48d89f1ff6c8", 
            "date": 1524675166305, 
            "discussionId": "1524675166278#mpc#3d0a2514-0831-4075-99ca-ff11d4348769", 
            "isEditable": false, 
            "isRead": false, 
            "isSynchronized": false, 
            "text": "Break is required, in case a future modification turns this into a case Refer: Rule 6-4-3, A switch statement shall be a well-formed switch statement."
          }
        ], 
        "discussionId": "1524675166278#mpc#3d0a2514-0831-4075-99ca-ff11d4348769", 
        "isStarred": true, 
        "labels": [
          {
            "colorId": "0", 
            "id": "60aecc5f-8b7e-4672-b8bb-6c73deb05b24", 
            "name": "accept"
          }
        ], 
        "read": 2, 
        "review": {
          "reviewId": {
            "projectId": "mpc", 
            "reviewId": "MPC-CR-1"
          }, 
          "state": 1, 
          "title": "develop"
        }
      }, 
      {
        "anchor": {
          "fileId": "/fsw/src/mpc_app.cpp", 
          "inlineInRevision": "2da519324634de7833bb5e99811e0e114beeef46", 
          "range": {
            "endOffset": 14125, 
            "startOffset": 14044
          }, 
          "revisionId": "2da519324634de7833bb5e99811e0e114beeef46"
        }, 
        "comments": [
          {
            "authorId": "3dc1e8a1-2e1f-446a-8179-97cc2b0e6423", 
            "commentId": "ced4d8fc-5f2e-4eb0-93fb-36824240bc88", 
            "date": 1524675117964, 
            "discussionId": "1524675117939#mpc#f51e8aab-a79e-4d2d-9f52-9c1784c62da0", 
            "isEditable": false, 
            "isRead": false, 
            "isSynchronized": false, 
            "text": "Remove this code"
          }
        ], 
        "discussionId": "1524675117939#mpc#f51e8aab-a79e-4d2d-9f52-9c1784c62da0", 
        "isStarred": true, 
        "labels": [
          {
            "colorId": "0", 
            "id": "60aecc5f-8b7e-4672-b8bb-6c73deb05b24", 
            "name": "accept"
          }
        ], 
        "read": 2, 
        "review": {
          "reviewId": {
            "projectId": "mpc", 
            "reviewId": "MPC-CR-1"
          }, 
          "state": 1, 
          "title": "develop"
        }
      }, 
      {
        "anchor": {
          "fileId": "/fsw/src/mpc_app.cpp", 
          "inlineInRevision": "2da519324634de7833bb5e99811e0e114beeef46", 
          "range": {
            "endOffset": 8777, 
            "startOffset": 8679
          }, 
          "revisionId": "2da519324634de7833bb5e99811e0e114beeef46"
        }, 
        "comments": [
          {
            "authorId": "3dc1e8a1-2e1f-446a-8179-97cc2b0e6423", 
            "commentId": "0c8052ba-b4af-40da-b774-456b42c18242", 
            "date": 1524674920537, 
            "discussionId": "1524674920179#mpc#3f9419ac-cc64-4c43-916c-d2fac8d9bce9", 
            "isEditable": false, 
            "isRead": false, 
            "isSynchronized": false, 
            "text": "Remove commented out code."
          }
        ], 
        "discussionId": "1524674920179#mpc#3f9419ac-cc64-4c43-916c-d2fac8d9bce9", 
        "isStarred": true, 
        "labels": [
          {
            "colorId": "0", 
            "id": "60aecc5f-8b7e-4672-b8bb-6c73deb05b24", 
            "name": "accept"
          }
        ], 
        "read": 2, 
        "review": {
          "reviewId": {
            "projectId": "mpc", 
            "reviewId": "MPC-CR-1"
          }, 
          "state": 1, 
          "title": "develop"
        }
      }, 
      {
        "anchor": {
          "fileId": "/fsw/src/mpc_app.cpp", 
          "inlineInRevision": "2da519324634de7833bb5e99811e0e114beeef46", 
          "range": {
            "endOffset": 2681, 
            "startOffset": 2662
          }, 
          "revisionId": "2da519324634de7833bb5e99811e0e114beeef46"
        }, 
        "comments": [
          {
            "authorId": "3dc1e8a1-2e1f-446a-8179-97cc2b0e6423", 
            "commentId": "71d2b5df-9bea-43ee-a205-bb320477a489", 
            "date": 1524674814030, 
            "discussionId": "1524674814003#mpc#0784521b-3abc-45ce-ae5b-ddfe99e6dd03", 
            "isEditable": false, 
            "isRead": false, 
            "isSynchronized": false, 
            "text": "Use return( iStatus );"
          }
        ], 
        "discussionId": "1524674814003#mpc#0784521b-3abc-45ce-ae5b-ddfe99e6dd03", 
        "isStarred": true, 
        "labels": [
          {
            "colorId": "0", 
            "id": "60aecc5f-8b7e-4672-b8bb-6c73deb05b24", 
            "name": "accept"
          }, 
          {
            "id": "style", 
            "name": "code style"
          }
        ], 
        "read": 2, 
        "review": {
          "reviewId": {
            "projectId": "mpc", 
            "reviewId": "MPC-CR-1"
          }, 
          "state": 1, 
          "title": "develop"
        }
      }, 
      {
        "anchor": {
          "fileId": "/fsw/src/mpc_app.cpp", 
          "inlineInRevision": "2da519324634de7833bb5e99811e0e114beeef46", 
          "range": {
            "endOffset": 506, 
            "startOffset": 488
          }, 
          "revisionId": "2da519324634de7833bb5e99811e0e114beeef46"
        }, 
        "comments": [
          {
            "authorId": "3dc1e8a1-2e1f-446a-8179-97cc2b0e6423", 
            "commentId": "c898557b-df81-42f1-8204-ddadf69c6d09", 
            "date": 1524674786572, 
            "discussionId": "1524674786531#mpc#8db76a30-1aee-486b-b7e8-a12d3d09498f", 
            "isEditable": false, 
            "isRead": false, 
            "isSynchronized": false, 
            "text": "Add this define under local definitions"
          }
        ], 
        "discussionId": "1524674786531#mpc#8db76a30-1aee-486b-b7e8-a12d3d09498f", 
        "isStarred": true, 
        "labels": [
          {
            "colorId": "0", 
            "id": "60aecc5f-8b7e-4672-b8bb-6c73deb05b24", 
            "name": "accept"
          }
        ], 
        "read": 2, 
        "review": {
          "reviewId": {
            "projectId": "mpc", 
            "reviewId": "MPC-CR-1"
          }, 
          "state": 1, 
          "title": "develop"
        }
      }, 
      {
        "anchor": {
          "fileId": "/fsw/src/mpc_app.cpp", 
          "inlineInRevision": "2da519324634de7833bb5e99811e0e114beeef46", 
          "range": {
            "endOffset": 199, 
            "startOffset": 199
          }, 
          "revisionId": "2da519324634de7833bb5e99811e0e114beeef46"
        }, 
        "comments": [
          {
            "authorId": "3dc1e8a1-2e1f-446a-8179-97cc2b0e6423", 
            "commentId": "a28a0e96-67b1-4929-a15d-c96c65a1d010", 
            "date": 1524674180824, 
            "discussionId": "1524674180787#mpc#34d4e08d-67c9-4b23-95e0-9a9dca39a398", 
            "isEditable": false, 
            "isRead": false, 
            "isSynchronized": false, 
            "text": "Remove extra white space between includes"
          }
        ], 
        "discussionId": "1524674180787#mpc#34d4e08d-67c9-4b23-95e0-9a9dca39a398", 
        "isStarred": true, 
        "labels": [
          {
            "colorId": "0", 
            "id": "60aecc5f-8b7e-4672-b8bb-6c73deb05b24", 
            "name": "accept"
          }
        ], 
        "read": 2, 
        "review": {
          "reviewId": {
            "projectId": "mpc", 
            "reviewId": "MPC-CR-1"
          }, 
          "state": 1, 
          "title": "develop"
        }
      }, 
      {
        "anchor": {
          "fileId": "/fsw/src/mpc_app.cpp", 
          "inlineInRevision": "2da519324634de7833bb5e99811e0e114beeef46", 
          "range": {
            "endOffset": 73, 
            "startOffset": 0
          }, 
          "revisionId": "2da519324634de7833bb5e99811e0e114beeef46"
        }, 
        "comments": [
          {
            "authorId": "3dc1e8a1-2e1f-446a-8179-97cc2b0e6423", 
            "commentId": "899f23a3-f695-4039-b630-258b733e3d7c", 
            "date": 1524674078652, 
            "discussionId": "1524674078624#mpc#e5bb4c93-e79d-4787-ad0d-cdf26711b787", 
            "isEditable": false, 
            "isRead": false, 
            "isSynchronized": false, 
            "text": "Missing license boilerplate"
          }
        ], 
        "discussionId": "1524674078624#mpc#e5bb4c93-e79d-4787-ad0d-cdf26711b787", 
        "isStarred": true, 
        "labels": [
          {
            "colorId": "0", 
            "id": "60aecc5f-8b7e-4672-b8bb-6c73deb05b24", 
            "name": "accept"
          }
        ], 
        "read": 2, 
        "review": {
          "reviewId": {
            "projectId": "mpc", 
            "reviewId": "MPC-CR-1"
          }, 
          "state": 1, 
          "title": "develop"
        }
      }, 
      {
        "anchor": {
          "fileId": "/fsw/src/mpc_app.h", 
          "inlineInRevision": "76ba3e459e78146462424682ae643a42dafc7dc7", 
          "range": {
            "endOffset": 12185, 
            "startOffset": 12121
          }, 
          "revisionId": "76ba3e459e78146462424682ae643a42dafc7dc7"
        }, 
        "comments": [
          {
            "authorId": "3dc1e8a1-2e1f-446a-8179-97cc2b0e6423", 
            "commentId": "c193730e-319d-4d76-a3c4-f08c74248d14", 
            "date": 1524674024665, 
            "discussionId": "1524674024657#mpc#a15492b7-689c-4077-9e6a-9e4f43be9ef9", 
            "isEditable": false, 
            "isRead": false, 
            "isSynchronized": false, 
            "text": "in / out, also see 391."
          }
        ], 
        "discussionId": "1524674024657#mpc#a15492b7-689c-4077-9e6a-9e4f43be9ef9", 
        "isStarred": true, 
        "labels": [
          {
            "colorId": "0", 
            "id": "60aecc5f-8b7e-4672-b8bb-6c73deb05b24", 
            "name": "accept"
          }
        ], 
        "read": 2, 
        "review": {
          "reviewId": {
            "projectId": "mpc", 
            "reviewId": "MPC-CR-1"
          }, 
          "state": 1, 
          "title": "develop"
        }
      }, 
      {
        "anchor": {
          "fileId": "/fsw/src/mpc_app.h", 
          "inlineInRevision": "76ba3e459e78146462424682ae643a42dafc7dc7", 
          "range": {
            "endOffset": 4753, 
            "startOffset": 4675
          }, 
          "revisionId": "76ba3e459e78146462424682ae643a42dafc7dc7"
        }, 
        "comments": [
          {
            "authorId": "3dc1e8a1-2e1f-446a-8179-97cc2b0e6423", 
            "commentId": "ebc78b6b-7b71-4f4d-bf1b-5afe26fdd084", 
            "date": 1524673915706, 
            "discussionId": "1524673915698#mpc#3a991412-bb51-4cc5-a077-180c518b5d01", 
            "isEditable": false, 
            "isRead": false, 
            "isSynchronized": false, 
            "text": "Global: Replace bool with CFE's boolean"
          }
        ], 
        "discussionId": "1524673915698#mpc#3a991412-bb51-4cc5-a077-180c518b5d01", 
        "isStarred": true, 
        "labels": [
          {
            "colorId": "0", 
            "id": "60aecc5f-8b7e-4672-b8bb-6c73deb05b24", 
            "name": "accept"
          }
        ], 
        "read": 2, 
        "review": {
          "reviewId": {
            "projectId": "mpc", 
            "reviewId": "MPC-CR-1"
          }, 
          "state": 1, 
          "title": "develop"
        }
      }, 
      {
        "anchor": {
          "fileId": "/fsw/src/mpc_app.h", 
          "inlineInRevision": "76ba3e459e78146462424682ae643a42dafc7dc7", 
          "range": {
            "endOffset": 3939, 
            "startOffset": 3885
          }, 
          "revisionId": "76ba3e459e78146462424682ae643a42dafc7dc7"
        }, 
        "comments": [
          {
            "authorId": "3dc1e8a1-2e1f-446a-8179-97cc2b0e6423", 
            "commentId": "954a80a2-bc0b-4125-9398-d21e195ec8eb", 
            "date": 1524673772503, 
            "discussionId": "1524673772497#mpc#f927dd1a-7826-40d0-a1ae-2e4887c408d0", 
            "isEditable": false, 
            "isRead": false, 
            "isSynchronized": false, 
            "text": "Global: Complete doxygen"
          }
        ], 
        "discussionId": "1524673772497#mpc#f927dd1a-7826-40d0-a1ae-2e4887c408d0", 
        "isStarred": true, 
        "labels": [
          {
            "colorId": "0", 
            "id": "60aecc5f-8b7e-4672-b8bb-6c73deb05b24", 
            "name": "accept"
          }
        ], 
        "read": 2, 
        "review": {
          "reviewId": {
            "projectId": "mpc", 
            "reviewId": "MPC-CR-1"
          }, 
          "state": 1, 
          "title": "develop"
        }
      }, 
      {
        "anchor": {
          "fileId": "/fsw/src/mpc_app.h", 
          "inlineInRevision": "76ba3e459e78146462424682ae643a42dafc7dc7", 
          "range": {
            "endOffset": 3559, 
            "startOffset": 3483
          }, 
          "revisionId": "76ba3e459e78146462424682ae643a42dafc7dc7"
        }, 
        "comments": [
          {
            "authorId": "3dc1e8a1-2e1f-446a-8179-97cc2b0e6423", 
            "commentId": "b62178fa-0210-44f4-9d98-79189e1dbdac", 
            "date": 1524673758331, 
            "discussionId": "1524673758325#mpc#22c95434-961d-4ddf-8d51-1b7a17c40dc1", 
            "isEditable": false, 
            "isRead": false, 
            "isSynchronized": false, 
            "text": "Remove commented out code."
          }
        ], 
        "discussionId": "1524673758325#mpc#22c95434-961d-4ddf-8d51-1b7a17c40dc1", 
        "isStarred": true, 
        "labels": [
          {
            "colorId": "0", 
            "id": "60aecc5f-8b7e-4672-b8bb-6c73deb05b24", 
            "name": "accept"
          }
        ], 
        "read": 2, 
        "review": {
          "reviewId": {
            "projectId": "mpc", 
            "reviewId": "MPC-CR-1"
          }, 
          "state": 1, 
          "title": "develop"
        }
      }, 
      {
        "anchor": {
          "fileId": "/fsw/src/mpc_app.h", 
          "inlineInRevision": "76ba3e459e78146462424682ae643a42dafc7dc7", 
          "range": {
            "endOffset": 2135, 
            "startOffset": 2135
          }, 
          "revisionId": "76ba3e459e78146462424682ae643a42dafc7dc7"
        }, 
        "comments": [
          {
            "authorId": "3dc1e8a1-2e1f-446a-8179-97cc2b0e6423", 
            "commentId": "faaafe7e-c89d-45f8-b644-1405fc31e664", 
            "date": 1524673726522, 
            "discussionId": "1524673726504#mpc#6328c3ab-db61-435f-9739-e49a2011dbb0", 
            "isEditable": false, 
            "isRead": false, 
            "isSynchronized": false, 
            "text": "Remove extra white space between includes"
          }
        ], 
        "discussionId": "1524673726504#mpc#6328c3ab-db61-435f-9739-e49a2011dbb0", 
        "isStarred": true, 
        "labels": [
          {
            "colorId": "0", 
            "id": "60aecc5f-8b7e-4672-b8bb-6c73deb05b24", 
            "name": "accept"
          }, 
          {
            "id": "style", 
            "name": "code style"
          }
        ], 
        "read": 2, 
        "review": {
          "reviewId": {
            "projectId": "mpc", 
            "reviewId": "MPC-CR-1"
          }, 
          "state": 1, 
          "title": "develop"
        }
      }, 
      {
        "anchor": {
          "fileId": "/fsw/src/mpc_config_utils.cpp", 
          "inlineInRevision": "c04e083b41d3d59042829e36c33f3269481896e4", 
          "range": {
            "endOffset": 5962, 
            "startOffset": 5884
          }, 
          "revisionId": "c04e083b41d3d59042829e36c33f3269481896e4"
        }, 
        "comments": [
          {
            "authorId": "3dc1e8a1-2e1f-446a-8179-97cc2b0e6423", 
            "commentId": "19f8021a-0244-43ea-8c98-9f5e0f8a68a0", 
            "date": 1524672950849, 
            "discussionId": "1524672950843#mpc#cbf8b5a9-d85e-41a4-927d-17203ed928dc", 
            "isEditable": false, 
            "isRead": false, 
            "isSynchronized": false, 
            "text": "Remove todo."
          }
        ], 
        "discussionId": "1524672950843#mpc#cbf8b5a9-d85e-41a4-927d-17203ed928dc", 
        "isStarred": true, 
        "labels": [
          {
            "colorId": "0", 
            "id": "60aecc5f-8b7e-4672-b8bb-6c73deb05b24", 
            "name": "accept"
          }
        ], 
        "read": 2, 
        "review": {
          "reviewId": {
            "projectId": "mpc", 
            "reviewId": "MPC-CR-1"
          }, 
          "state": 1, 
          "title": "develop"
        }
      }, 
      {
        "anchor": {
          "fileId": "/fsw/src/mpc_config_utils.cpp", 
          "inlineInRevision": "c04e083b41d3d59042829e36c33f3269481896e4", 
          "range": {
            "endOffset": 4198, 
            "startOffset": 4156
          }, 
          "revisionId": "c04e083b41d3d59042829e36c33f3269481896e4"
        }, 
        "comments": [
          {
            "authorId": "3dc1e8a1-2e1f-446a-8179-97cc2b0e6423", 
            "commentId": "3b61cf09-63b5-4257-8209-019ebcc8d19f", 
            "date": 1524672830062, 
            "discussionId": "1524672830056#mpc#540e4ac1-4346-43e8-9db7-5071bf88accf", 
            "isEditable": false, 
            "isRead": false, 
            "isSynchronized": false, 
            "text": "Remove todo and you may want to complete validation"
          }
        ], 
        "discussionId": "1524672830056#mpc#540e4ac1-4346-43e8-9db7-5071bf88accf", 
        "isStarred": true, 
        "labels": [
          {
            "colorId": "0", 
            "id": "60aecc5f-8b7e-4672-b8bb-6c73deb05b24", 
            "name": "accept"
          }
        ], 
        "read": 2, 
        "review": {
          "reviewId": {
            "projectId": "mpc", 
            "reviewId": "MPC-CR-1"
          }, 
          "state": 1, 
          "title": "develop"
        }
      }, 
      {
        "anchor": {
          "fileId": "/fsw/src/mpc_events.h", 
          "inlineInRevision": "e9934d33c5c5d3a24af9bc830c65303ff97958bf", 
          "range": {
            "endOffset": 5217, 
            "startOffset": 5190
          }, 
          "revisionId": "e9934d33c5c5d3a24af9bc830c65303ff97958bf"
        }, 
        "comments": [
          {
            "authorId": "3dc1e8a1-2e1f-446a-8179-97cc2b0e6423", 
            "commentId": "b3a99c21-9cef-4828-a35c-406359fe2175", 
            "date": 1524672351360, 
            "discussionId": "1524672351353#mpc#e68c88c5-41b1-4b63-b7e6-595a3a25d7db", 
            "isEditable": false, 
            "isRead": false, 
            "isSynchronized": false, 
            "text": "Add numerical values to all enumerations"
          }
        ], 
        "discussionId": "1524672351353#mpc#e68c88c5-41b1-4b63-b7e6-595a3a25d7db", 
        "isStarred": true, 
        "labels": [
          {
            "colorId": "0", 
            "id": "60aecc5f-8b7e-4672-b8bb-6c73deb05b24", 
            "name": "accept"
          }
        ], 
        "read": 2, 
        "review": {
          "reviewId": {
            "projectId": "mpc", 
            "reviewId": "MPC-CR-1"
          }, 
          "state": 1, 
          "title": "develop"
        }
      }, 
      {
        "anchor": {
          "fileId": "/fsw/src/mpc_tbldefs.h", 
          "inlineInRevision": "c0d7e331735e5b8a25d2077cd9872ba55a2b1dbc", 
          "range": {
            "endOffset": 14478, 
            "startOffset": 14453
          }, 
          "revisionId": "c0d7e331735e5b8a25d2077cd9872ba55a2b1dbc"
        }, 
        "comments": [
          {
            "authorId": "3dc1e8a1-2e1f-446a-8179-97cc2b0e6423", 
            "commentId": "3d994a77-61ad-4b89-9466-6e4e9638c21c", 
            "date": 1524672288882, 
            "discussionId": "1524672288873#mpc#7178655c-3167-47c3-a2e2-7a5950c76212", 
            "isEditable": false, 
            "isRead": false, 
            "isSynchronized": false, 
            "text": "Missing doxygen"
          }
        ], 
        "discussionId": "1524672288873#mpc#7178655c-3167-47c3-a2e2-7a5950c76212", 
        "isStarred": true, 
        "labels": [
          {
            "colorId": "0", 
            "id": "60aecc5f-8b7e-4672-b8bb-6c73deb05b24", 
            "name": "accept"
          }
        ], 
        "read": 2, 
        "review": {
          "reviewId": {
            "projectId": "mpc", 
            "reviewId": "MPC-CR-1"
          }, 
          "state": 1, 
          "title": "develop"
        }
      }
    ], 
    "hasMore": false, 
    "totalCount": 49
  }
}
